tool/__init__.py
wttest/__init__.py
wttest/wtftest.py
test_deng_s223-1.0.1.dist-info/LICENSE
test_deng_s223-1.0.1.dist-info/METADATA
test_deng_s223-1.0.1.dist-info/WHEEL
test_deng_s223-1.0.1.dist-info/top_level.txt
test_deng_s223-1.0.1.dist-info/RECORD
